HISTORY.rst
MANIFEST.in
README.rst
setup.py
ilogin/__init__.py
ilogin/ilogin.py
ilogin/ilogin2.py
ilogin/ilogin3.py
ilogin.egg-info/PKG-INFO
ilogin.egg-info/SOURCES.txt
ilogin.egg-info/dependency_links.txt
ilogin.egg-info/entry_points.txt
ilogin.egg-info/top_level.txt