Metadata-Version: 2.1
Name: ilogin
Version: 4.1
Summary: Single Sign-On script (SSO) that allows you to generate unique passwords for each online and offline service you're using.
Home-page: http://github.com/avoinea/ilogin
Author: Alin Voinea
Author-email: alin.voinea@gmail.com
License: GPL
Platform: UNKNOWN
Classifier: Environment :: Console
Classifier: Intended Audience :: Developers
Classifier: Programming Language :: Python
Classifier: Operating System :: OS Independent
Classifier: Topic :: Software Development :: Libraries :: Python Modules
